{
  "value": "飢",
  "strokes": [
    "M30.79,13.5c0.06,0.73,0.23,1.95-0.12,2.93C27.79,24.57,20.25,35.5,10.75,43.5",
    "M32.5,19.25c5.56,3.31,9.9,6.84,14.25,11.25",
    "M30.79,32.26c0.85,0.85,1.28,2.11,1.28,3.32c0,0.93-0.07,4.37-0.07,6.67",
    "M18.87,44.76c1.63,0.49,3.54,0.26,5.33-0.06c4.23-0.75,11.07-2.05,14.19-2.61c2.91-0.53,4.65,0,4.21,3.3c-0.67,4.98-1.12,10.62-1.69,15.63c-0.19,1.64-0.39,3.22-0.62,4.68",
    "M21.71,55.03c3.42-0.41,12.54-1.91,19.03-2.66",
    "M21.62,65.85c4.11-0.43,11.38-1.23,17.71-1.97",
    "M19.62,45.51c0.75,0.75,1.03,1.49,1.03,2.49c0,0.93-0.02,39.28-0.02,43.25c0,2.08,0.66,2.69,2.7,1.08c2.04-1.61,10.3-8.58,16.43-13.58",
    "M36.38,72c2.59,2.25,6.65,8.25,8.12,13",
    "M57.86,25.82c0.84,0.84,1.45,1.93,1.45,3.78c0,19.84,0.69,45.9-11.49,60.4",
    "M60.16,28.86c5.59-1.73,10.47-2.98,13.98-3.86c2.82-0.71,4.72,0.44,4.72,4.1c0,4.16-0.07,51.87-0.07,54.52c0,6.51,1.47,8.72,8.74,8.72c6.47,0,7.28-1.33,7.28-9.42"
  ],
  "kun": [
    "う.える"
  ],
  "on": [
    "キ"
  ],
  "frequency": 1659,
  "meanings": [
    {
      "lang": "en",
      "values": [
        "hungry",
        "starve"
      ]
    },
    {
      "lang": "fr",
      "values": [
        "faim",
        "famine"
      ]
    },
    {
      "lang": "es",
      "values": [
        "hambre",
        "tener hambre"
      ]
    },
    {
      "lang": "pt",
      "values": [
        "faminto",
        "morrer de fome"
      ]
    }
  ],
  "radicals": [
    {
      "radical": "飠",
      "startStroke": 0,
      "strokes": 8
    },
    {
      "radical": "丿",
      "startStroke": 8,
      "strokes": 1
    },
    {
      "radical": "几",
      "startStroke": 8,
      "strokes": 2
    }
  ],
  "sentences": [
    {
      "content": "私は飢えた蜘蛛です。",
      "furigana": "[私|わたし]は[飢|う]えた[蜘蛛|くも]です。",
      "translation_zh_CN": "我是一只饿了的蜘蛛。"
    },
    {
      "content": "その男は飢えている。",
      "furigana": "その[男|おとこ]は[飢|う]えている。",
      "translation_zh_CN": "那人饿着呢."
    },
    {
      "content": "避難民たちは飢えと闘った。",
      "furigana": "[避難|ひ|なん][民|みん]たちは[飢|う]えと[闘|たたか]った。",
      "translation_zh_CN": "难民与饥饿作斗争。"
    },
    {
      "content": "労働者の多くは飢えで死んだ。",
      "furigana": "[労働|ろう|どう][者|しゃ]の[多|おお]くは[飢|う]えで[死|し]んだ。",
      "translation_zh_CN": "许多工人死于饥饿。"
    },
    {
      "content": "世界では多くの人が飢えている。",
      "furigana": "[世界|せ|かい]では[多|おお]くの[人|ひと]が[飢|う]えている。",
      "translation_zh_CN": "世界上许多人很饥饿。"
    },
    {
      "content": "毎年何百万という人が飢えで死んでいる。",
      "furigana": "[毎年|まい|とし][何|なん][百|びゃく][万|まん]という[人|ひと]が[飢|う]えで[死|し]んでいる。",
      "translation_zh_CN": "每年有几百万人死于饥饿。"
    },
    {
      "content": "盗みをするよりも飢え死にした方がましだ。",
      "furigana": "[盗|ぬす]みをするよりも[飢|う]え[死|じ]にした[方|ほう]がましだ。",
      "translation_zh_CN": "我寧願餓死，也不會去偷東西。"
    },
    {
      "content": "盗みをするくらいなら飢え死にした方がましだ。",
      "furigana": "[盗|ぬす]みをするくらいなら[飢|う]え[死|じ]にした[方|ほう]がましだ。",
      "translation_zh_CN": "我寧願餓死，也不會去偷東西。"
    },
    {
      "content": "世界には、神がパン以外の形をとって彼らの前に現れることが不可能なほど、飢えている人たちがいます。",
      "furigana": "[世界|せ|かい]には、[神|かみ]がパン[以外|い|がい]の[形|かたち]をとって[彼|かれ]らの[前|まえ]に[現|あらわ]れることが[不可能|ふ|か|のう]なほど、[飢|う]えている[人|ひと]たちがいます。",
      "translation_zh_CN": "这世上有人如此贪婪，以至于除非上帝以面包的形式出现在他的面前，他是看不到上帝的。"
    }
  ],
  "usages": [
    {
      "slug": "飢饉",
      "jlpt": [
        "jlpt-n2"
      ],
      "japanese": [
        {
          "word": "飢饉",
          "reading": "ききん"
        },
        {
          "word": "飢きん",
          "reading": "ききん"
        },
        {
          "word": "饑饉",
          "reading": "ききん"
        }
      ]
    },
    {
      "slug": "飢える",
      "jlpt": [
        "jlpt-n2"
      ],
      "japanese": [
        {
          "word": "飢える",
          "reading": "うえる"
        },
        {
          "word": "餓える",
          "reading": "うえる"
        },
        {
          "word": "饑える",
          "reading": "うえる"
        },
        {
          "word": "飢える",
          "reading": "かつえる"
        },
        {
          "word": "餓える",
          "reading": "かつえる"
        }
      ]
    },
    {
      "slug": "飢え",
      "jlpt": [],
      "japanese": [
        {
          "word": "飢え",
          "reading": "うえ"
        },
        {
          "word": "餓え",
          "reading": "うえ"
        },
        {
          "word": "饑え",
          "reading": "うえ"
        }
      ]
    },
    {
      "slug": "飢餓",
      "jlpt": [],
      "japanese": [
        {
          "word": "飢餓",
          "reading": "きが"
        },
        {
          "word": "饑餓",
          "reading": "きが"
        }
      ]
    },
    {
      "slug": "飢え死に",
      "jlpt": [],
      "japanese": [
        {
          "word": "飢え死に",
          "reading": "うえじに"
        },
        {
          "word": "飢え死に",
          "reading": "かつえじに"
        },
        {
          "word": "餓え死に",
          "reading": "うえじに"
        },
        {
          "word": "餓え死に",
          "reading": "かつえじに"
        },
        {
          "word": "飢死に",
          "reading": "うえじに"
        },
        {
          "word": "飢死に",
          "reading": "かつえじに"
        },
        {
          "word": "飢え死",
          "reading": "うえじに"
        },
        {
          "word": "飢え死",
          "reading": "かつえじに"
        },
        {
          "word": "飢死",
          "reading": "うえじに"
        },
        {
          "word": "飢死",
          "reading": "かつえじに"
        },
        {
          "word": "饑死",
          "reading": "うえじに"
        },
        {
          "word": "饑死",
          "reading": "かつえじに"
        }
      ]
    },
    {
      "slug": "餓えに苦しむ",
      "jlpt": [],
      "japanese": [
        {
          "word": "飢えに苦しむ",
          "reading": "うえにくるしむ"
        },
        {
          "word": "餓えに苦しむ",
          "reading": "うえにくるしむ"
        }
      ]
    },
    {
      "slug": "飢餓療法",
      "jlpt": [],
      "japanese": [
        {
          "word": "飢餓療法",
          "reading": "きがりょうほう"
        }
      ]
    },
    {
      "slug": "飢寒",
      "jlpt": [],
      "japanese": [
        {
          "word": "飢寒",
          "reading": "きかん"
        },
        {
          "word": "饑寒",
          "reading": "きかん"
        }
      ]
    },
    {
      "slug": "飢餓線上に",
      "jlpt": [],
      "japanese": [
        {
          "word": "飢餓線上に",
          "reading": "きがせんじょうに"
        }
      ]
    },
    {
      "slug": "飢凍",
      "jlpt": [],
      "japanese": [
        {
          "word": "飢凍",
          "reading": "きとう"
        }
      ]
    },
    {
      "slug": "飢民",
      "jlpt": [],
      "japanese": [
        {
          "word": "飢民",
          "reading": "きみん"
        }
      ]
    },
    {
      "slug": "飢渇",
      "jlpt": [],
      "japanese": [
        {
          "word": "飢渇",
          "reading": "きかつ"
        },
        {
          "word": "饑渇",
          "reading": "きかつ"
        }
      ]
    },
    {
      "slug": "飢餓感",
      "jlpt": [],
      "japanese": [
        {
          "word": "飢餓感",
          "reading": "きがかん"
        }
      ]
    },
    {
      "slug": "飢えたる犬は棒を恐れず",
      "jlpt": [],
      "japanese": [
        {
          "word": "飢えたる犬は棒を恐れず",
          "reading": "うえたるいぬはぼうをおそれず"
        }
      ]
    },
    {
      "slug": "飢え凍える",
      "jlpt": [],
      "japanese": [
        {
          "word": "飢え凍える",
          "reading": "うえこごえる"
        }
      ]
    }
  ]
}