{
  "value": "員",
  "strokes": [
    "M29.04,13.85c1.09,0.77,1.78,2.04,1.96,2.9c0.87,4.12,1.77,9.71,2.58,14.73c0.15,0.94,0.29,1.87,0.42,2.76",
    "M31.49,15.19c12.02-1.41,37.9-4.06,42.45-4.45c2.81-0.24,4.31,1.14,3.63,3.71c-0.95,3.6-2.32,8.34-3.48,12.58",
    "M34.2,32.08c4.98-0.5,26.33-2.41,37.31-3.51c1.81-0.18,3.33-0.34,4.46-0.46",
    "M32.89,41.39c0.67,0.91,1.16,2.09,1.16,3.3c0,0.99-0.15,24.66-0.08,34.05c0.02,2.14,0.04,3.54,0.08,3.76",
    "M34.75,42.49c9.25-0.77,34.46-3.1,37.37-3.25c2.9-0.15,4.63,1.26,4.45,3.97c-0.21,3.08-0.64,24.88-0.79,33.54c-0.04,1.97-0.06,3.73-0.06,3.9",
    "M35.11,54.59c9.26-0.71,31.26-2.34,40.03-2.72",
    "M35.42,66.76c10.7-0.76,28.7-2.13,39.27-2.57",
    "M35.16,79.89c9.34-0.64,30.46-2.27,39.27-2.57",
    "M41.62,85c0.23,1.71-0.49,2.79-1.44,3.6C37.3,91.03,28.4,97,22.62,99.88",
    "M67.5,84.75c7.62,3.98,17.17,11.76,19.25,15.25"
  ],
  "on": [
    "イン"
  ],
  "frequency": 54,
  "meanings": [
    {
      "lang": "en",
      "values": [
        "employee",
        "member",
        "number",
        "the one in charge"
      ]
    },
    {
      "lang": "fr",
      "values": [
        "employé",
        "membre",
        "nombre (de personnes)",
        "personne en charge"
      ]
    },
    {
      "lang": "es",
      "values": [
        "empleado",
        "miembro",
        "personal"
      ]
    },
    {
      "lang": "pt",
      "values": [
        "empregado",
        "membro",
        "número",
        "encarregado"
      ]
    }
  ],
  "radicals": [
    {
      "radical": "口",
      "startStroke": 0,
      "strokes": 3
    },
    {
      "radical": "目",
      "startStroke": 3,
      "strokes": 5
    },
    {
      "radical": "貝",
      "startStroke": 3,
      "strokes": 7
    },
    {
      "radical": "八",
      "startStroke": 8,
      "strokes": 2
    }
  ],
  "sentences": [
    {
      "content": "会社員です。",
      "furigana": "[会社員|かい|しゃ|いん]です。",
      "translation_zh_CN": "我是公司职员。"
    },
    {
      "content": "乗組員が多い。",
      "furigana": "[乗組員|のり|くみ|いん]が[多|おお]い。",
      "translation_zh_CN": "船员有很多。"
    },
    {
      "content": "私は会社員です。",
      "furigana": "[私|わたし]は[会社員|かい|しゃ|いん]です。",
      "translation_zh_CN": "我是一名办公室职员。"
    },
    {
      "content": "審査員は誰ですか？",
      "furigana": "[審査員|しん|さ|いん]は[誰|だれ]ですか？",
      "translation_zh_CN": "评委是谁？"
    },
    {
      "content": "乗務員は皆疲れていた。",
      "furigana": "[乗務員|じょう|む|いん]は[皆疲|みな|つか]れていた。",
      "translation_zh_CN": "船员们都累了。"
    },
    {
      "content": "私は銀行員です。",
      "furigana": "[私|わたし]は[銀行員|ぎん|こう|いん]です。",
      "translation_zh_CN": "我是银行业工作者。"
    },
    {
      "content": "彼は会社員です。",
      "furigana": "[彼|かれ]は[会社員|かい|しゃ|いん]です。",
      "translation_zh_CN": "他是一名办公室职员。"
    },
    {
      "content": "彼は銀行員です。",
      "furigana": "[彼|かれ]は[銀行員|ぎん|こう|いん]です。",
      "translation_zh_CN": "他是一名银行职员。"
    },
    {
      "content": "乗組員は全員救われた。",
      "furigana": "[乗組員|のり|くみ|いん]は[全員救|ぜん|いん|すく]われた。",
      "translation_zh_CN": "所有船员均获救。"
    },
    {
      "content": "私は販売員です。",
      "furigana": "[私|わたし]は[販売員|はん|ばい|いん]です。",
      "translation_zh_CN": "我是一名销售人员。"
    },
    {
      "content": "私は会社員です。",
      "furigana": "[私|わたし]は[会社|かい|しゃ][員|いん]です。",
      "translation_zh_CN": "我是个职员。"
    },
    {
      "content": "私は銀行員です。",
      "furigana": "[私|わたし]は[銀行員|ぎん|こう|いん]です。",
      "translation_zh_CN": "我是一名银行职员。"
    },
    {
      "content": "バスは満員だった。",
      "furigana": "バスは[満員|まん|いん]だった。",
      "translation_zh_CN": "这辆公车客满了。"
    },
    {
      "content": "彼は野球部の一員だ。",
      "furigana": "[彼|かれ]は[野球|や|きゅう][部|ぶ]の[一員|いち|いん]だ。",
      "translation_zh_CN": "他是这棒球俱乐部的成员。"
    },
    {
      "content": "全員静かにしなさい。",
      "furigana": "[全員|ぜん|いん][静|しず]かにしなさい。",
      "translation_zh_CN": "你们所有的人都安静。"
    },
    {
      "content": "全員が出席していた。",
      "furigana": "[全員|ぜん|いん]が[出席|しゅっ|せき]していた。",
      "translation_zh_CN": "大家齐了。"
    },
    {
      "content": "私の父は会社員です。",
      "furigana": "[私|わたし]の[父|ちち]は[会社|かい|しゃ][員|いん]です。",
      "translation_zh_CN": "我父亲是一名办公室职员。"
    },
    {
      "content": "ビルは編集部員です。",
      "furigana": "ビルは[編集|へん|しゅう][部員|ぶ|いん]です。",
      "translation_zh_CN": "比尔在编辑部工作。"
    },
    {
      "content": "姉は英語の教員です。",
      "furigana": "[姉|あね]は[英語|えい|ご]の[教員|きょう|いん]です。",
      "translation_zh_CN": "我姊姊是个英语教师。"
    },
    {
      "content": "彼は委員会の委員長だ。",
      "furigana": "[彼|かれ]は[委員|い|いん][会|かい]の[委員|い|いん][長|ちょう]だ。",
      "translation_zh_CN": "他是委员会主席。"
    }
  ],
  "usages": [
    {
      "slug": "員数",
      "jlpt": [],
      "japanese": [
        {
          "word": "員数",
          "reading": "いんずう"
        },
        {
          "word": "員数",
          "reading": "いんず"
        },
        {
          "word": "員数",
          "reading": "いんじゅ"
        },
        {
          "word": "員數",
          "reading": "いんずう"
        },
        {
          "word": "員數",
          "reading": "いんず"
        },
        {
          "word": "員數",
          "reading": "いんじゅ"
        }
      ]
    },
    {
      "slug": "員外",
      "jlpt": [],
      "japanese": [
        {
          "word": "員外",
          "reading": "いんがい"
        }
      ]
    },
    {
      "slug": "員名",
      "jlpt": [],
      "japanese": [
        {
          "word": "員名",
          "reading": "いんめい"
        }
      ]
    },
    {
      "slug": "員に備わるのみ",
      "jlpt": [],
      "japanese": [
        {
          "word": "員に備わるのみ",
          "reading": "いんにそなわるのみ"
        }
      ]
    }
  ]
}