{
  "value": "異",
  "strokes": [
    "M27.85,13.89c0.82,0.82,0.95,2.23,1.15,3.24c1.87,9.5,2.71,14.21,3.78,22.85c0.17,1.38,0.32,2.74,0.45,4.03",
    "M30.08,16.45c17.04-2.2,35.29-3.95,46.87-4.72c2.43-0.16,3.68,1.77,3.17,4.29c-1.03,5.14-2.89,13.7-5.44,21.79c-0.35,1.1-0.71,2.21-1.09,3.3",
    "M53.18,15.8c0.95,0.95,1.2,2.33,1.2,3.45c0,6.99-0.02,12-0.02,19.76",
    "M32.39,29.18c8.23-1.06,37.73-3.68,44.31-3.82",
    "M34.42,41.86C46,40.5,64.25,39.5,73.21,39.02",
    "M26.35,56.7c2.32,0.64,4.71,0.14,7.04-0.11c9.12-0.96,29.62-3.21,40.24-4.12c2.41-0.21,4.86-0.24,7.25,0.15",
    "M41.22,49.55c0.8,0.8,1.02,2.23,1.02,2.79c0.01,5.66,0.01,12.16,0,19.21",
    "M66.24,45.5c0.76,0.76,1.01,1.88,0.94,2.93C66.4,58.71,66,62,65.36,69.74",
    "M15.73,74.13c3.15,0.85,6.58,0.35,9.78,0.07c13.13-1.14,44.37-4.17,58.36-4.92c3.01-0.16,5.92-0.25,8.9,0.24",
    "M39.41,81.33c0.09,0.92,0.02,1.92-0.86,3.06c-2.88,3.72-9.9,8.83-17.61,12.96",
    "M65.84,80.53C72.75,85,79.12,91.75,82.92,98.47"
  ],
  "kun": [
    "こと",
    "こと.なる",
    "け"
  ],
  "on": [
    "イ"
  ],
  "frequency": 631,
  "meanings": [
    {
      "lang": "en",
      "values": [
        "uncommon",
        "different",
        "queerness",
        "strangeness",
        "wonderful",
        "curious",
        "unusual"
      ]
    },
    {
      "lang": "fr",
      "values": [
        "inhabituel",
        "bizarrerie",
        "étrangeté",
        "surprenant",
        "curieux",
        "extraordinaire"
      ]
    },
    {
      "lang": "es",
      "values": [
        "raro",
        "extraño",
        "inusual",
        "diferente"
      ]
    },
    {
      "lang": "pt",
      "values": [
        "incomum",
        "esquisito",
        "estranho",
        "raro",
        "curioso",
        "maravilhoso"
      ]
    }
  ],
  "radicals": [
    {
      "radical": "田",
      "startStroke": 0,
      "strokes": 5
    },
    {
      "radical": "共",
      "startStroke": 5,
      "strokes": 6
    },
    {
      "radical": "八",
      "startStroke": 9,
      "strokes": 2
    }
  ],
  "sentences": [
    {
      "content": "モーターから異音がしている。",
      "furigana": "モーターから[異音|いおん]がしている。",
      "translation_zh_CN": "电机发出奇怪的噪音。"
    },
    {
      "content": "子供はみんな異邦人だ。",
      "furigana": "[子供|こ|ども]はみんな[異邦人|い|ほう|じん]だ。",
      "translation_zh_CN": "所有的孩子都是外国人。"
    },
    {
      "content": "異文化の生活に適応するのは一般に難しい。",
      "furigana": "[異文化|い|ぶん|か]の[生活|せい|かつ]に[適応|てき|おう]するのは[一般|いっ|ぱん]に[難|むずか]しい。",
      "translation_zh_CN": "一般来说，适应不同文化中的生活是很困难的。"
    },
    {
      "content": "異文化間のコミュニケーションはとてもむずかしいです。",
      "furigana": "[異文化間|い|ぶん|か|かん]のコミュニケーションはとてもむずかしいです。",
      "translation_zh_CN": "跨文化交流是非常困难的。"
    },
    {
      "content": "アンチケモナーらはインターネット上で誇らしげにケモナーらに対して異を唱えた。",
      "furigana": "アンチケモナーらはインターネット[上|じょう]で[誇|ほこ]らしげにケモナーらに[対|たい]して[異|こと]を[唱|とな]えた。",
      "translation_zh_CN": "反化学者自豪地在互联网上公开反对化学者。"
    },
    {
      "content": "「本当にゴミでいっぱいなんだ」と言われ、部屋のドアを開けたところ、そこはまさに異世界だった。",
      "furigana": "「[本当|ほん|とう]にゴミでいっぱいなんだ」と[言|い]われ、[部屋|へ|や]のドアを[開|あ]けたところ、そこはまさに[異世界|い|せ|かい]だった。",
      "translation_zh_CN": "“这里真的到处都是垃圾，”他说，当他打开房间门时，他进入了一个完全不同的世界。"
    },
    {
      "content": "西部戦線異状なし",
      "furigana": "[西部|せい|ぶ][戦線|せん|せん][異状|い|じょう]なし",
      "translation_zh_CN": "西线无战事"
    },
    {
      "content": "何か異議がありますか？",
      "furigana": "[何|なに]か[異議|い|ぎ]がありますか？",
      "translation_zh_CN": "有什么不同意见吗？"
    },
    {
      "content": "僕の考えは君と異なる。",
      "furigana": "[僕|ぼく]の[考|かんが]えは[君|きみ]と[異|こと]なる。",
      "translation_zh_CN": "我的想法跟你不一样。"
    },
    {
      "content": "子供はみんな異邦人だ。",
      "furigana": "[子供|こ|ども]はみんな[異邦|い|ほう][人|じん]だ。",
      "translation_zh_CN": "小朋友都是外国人。"
    },
    {
      "content": "僕は異常な物音を聞いた。",
      "furigana": "[僕|ぼく]は[異常|い|じょう]な[物音|もの|おと]を[聞|き]いた。",
      "translation_zh_CN": "我听到一个不寻常的声音。"
    },
    {
      "content": "社会の習慣は国によって異なる。",
      "furigana": "[社会|しゃ|かい]の[習慣|しゅう|かん]は[国|くに]によって[異|こと]なる。",
      "translation_zh_CN": "国家不同，习俗各异。"
    },
    {
      "content": "ロンドンは気候が東京と異なる。",
      "furigana": "ロンドンは[気候|き|こう]が[東京|とう|きょう]と[異|こと]なる。",
      "translation_zh_CN": "伦敦的气候和东京不同。"
    },
    {
      "content": "こってり化粧した顔は異様である。",
      "furigana": "こってり[化粧|け|しょう]した[顔|かお]は[異様|い|よう]である。",
      "translation_zh_CN": "化妆太浓的话脸会看着很奇怪。"
    },
    {
      "content": "ここ何年か異常気象がつづいている。",
      "furigana": "ここ[何|なん][年|ねん]か[異常|い|じょう][気象|き|しょう]がつづいている。",
      "translation_zh_CN": "这几年的天气很反常。"
    },
    {
      "content": "環境汚染は、異常気象を誘発している。",
      "furigana": "[環境|かん|きょう][汚染|お|せん]は、[異常|い|じょう][気象|き|しょう]を[誘発|ゆう|はつ]している。",
      "translation_zh_CN": "环境污染正造成异常的天气情况。"
    }
  ],
  "usages": [
    {
      "slug": "異常",
      "jlpt": [
        "jlpt-n3"
      ],
      "japanese": [
        {
          "word": "異常",
          "reading": "いじょう"
        }
      ]
    },
    {
      "slug": "異なる",
      "jlpt": [
        "jlpt-n3"
      ],
      "japanese": [
        {
          "word": "異なる",
          "reading": "ことなる"
        },
        {
          "word": "異る",
          "reading": "ことなる"
        }
      ]
    },
    {
      "slug": "異議",
      "jlpt": [
        "jlpt-n1"
      ],
      "japanese": [
        {
          "word": "異議",
          "reading": "いぎ"
        }
      ]
    },
    {
      "slug": "異論",
      "jlpt": [
        "jlpt-n1"
      ],
      "japanese": [
        {
          "word": "異論",
          "reading": "いろん"
        }
      ]
    },
    {
      "slug": "異性",
      "jlpt": [
        "jlpt-n1"
      ],
      "japanese": [
        {
          "word": "異性",
          "reading": "いせい"
        }
      ]
    },
    {
      "slug": "異端",
      "jlpt": [],
      "japanese": [
        {
          "word": "異端",
          "reading": "いたん"
        }
      ]
    },
    {
      "slug": "違和感",
      "jlpt": [],
      "japanese": [
        {
          "word": "違和感",
          "reading": "いわかん"
        }
      ]
    },
    {
      "slug": "異状",
      "jlpt": [],
      "japanese": [
        {
          "word": "異状",
          "reading": "いじょう"
        }
      ]
    },
    {
      "slug": "異様",
      "jlpt": [],
      "japanese": [
        {
          "word": "異様",
          "reading": "いよう"
        }
      ]
    },
    {
      "slug": "異質",
      "jlpt": [],
      "japanese": [
        {
          "word": "異質",
          "reading": "いしつ"
        }
      ]
    },
    {
      "slug": "異色",
      "jlpt": [],
      "japanese": [
        {
          "word": "異色",
          "reading": "いしょく"
        }
      ]
    },
    {
      "slug": "異例",
      "jlpt": [],
      "japanese": [
        {
          "word": "異例",
          "reading": "いれい"
        }
      ]
    },
    {
      "slug": "異名",
      "jlpt": [],
      "japanese": [
        {
          "word": "異名",
          "reading": "いみょう"
        },
        {
          "word": "異名",
          "reading": "いめい"
        }
      ]
    },
    {
      "slug": "異口同音",
      "jlpt": [],
      "japanese": [
        {
          "word": "異口同音",
          "reading": "いくどうおん"
        },
        {
          "word": "異口同音",
          "reading": "いこうどうおん"
        }
      ]
    },
    {
      "slug": "異存",
      "jlpt": [],
      "japanese": [
        {
          "word": "異存",
          "reading": "いぞん"
        }
      ]
    },
    {
      "slug": "異彩",
      "jlpt": [],
      "japanese": [
        {
          "word": "異彩",
          "reading": "いさい"
        }
      ]
    },
    {
      "slug": "異母",
      "jlpt": [],
      "japanese": [
        {
          "word": "異母",
          "reading": "いぼ"
        }
      ]
    },
    {
      "slug": "異常気象",
      "jlpt": [],
      "japanese": [
        {
          "word": "異常気象",
          "reading": "いじょうきしょう"
        }
      ]
    }
  ]
}