{
  "value": "貼",
  "strokes": [
    "M17.3,22.18c0.36,1.17,0.88,2.04,0.88,3.6c0,1.56-0.39,40.97-0.24,46.11",
    "M18.28,23.67c2.03-0.19,17.49-3.19,19.34-3.42c1.54-0.19,2.75,1.09,2.62,2.53c-0.17,1.83-0.22,34.97-0.6,46.67",
    "M18.24,37.62c7.85-0.76,19.14-2.66,20.89-2.66",
    "M17.91,53.45c7.75-0.95,13.02-1.45,21.54-2.34",
    "M18.43,69.48c4.03,0,15.88-2.34,21.1-2.34",
    "M23.62,77.73c0.26,1.18,0.52,1.5,0,2.36c-1.57,2.59-7.3,10.59-10.45,13.66",
    "M35.51,75.2c3.69,4.36,8.06,12.27,9.07,16.08",
    "M67.81,14.63c0.76,0.45,2.36,3.35,2.51,4.25c0.15,0.9-0.25,34.12-0.25,47.25",
    "M70.25,41.24c8.82-0.91,18.12-2.73,19.34-2.73c1.23,0,3.43,0,4.41,0.3",
    "M53.91,67.55c0.41,0.46,0.82,0.84,1,1.41c1.41,4.54,3.09,17.05,4.05,25.2",
    "M54.71,68.19c10.79-1.69,29.64-3.07,34.75-3.71c1.87-0.23,2.99,2.36,2.73,3.75c-1.11,5.71-3.49,14.04-5.02,21.28",
    "M58.86,91.66C66.5,91.25,79.5,90,89.54,89.72"
  ],
  "kun": [
    "は.る",
    "つ.く"
  ],
  "on": [
    "テン",
    "チョウ"
  ],
  "frequency": 2444,
  "meanings": [
    {
      "lang": "en",
      "values": [
        "stick",
        "paste",
        "apply"
      ]
    },
    {
      "lang": "es",
      "values": [
        "pegar",
        "engomar",
        "aplicar"
      ]
    }
  ],
  "radicals": [
    {
      "radical": "目",
      "startStroke": 0,
      "strokes": 5
    },
    {
      "radical": "貝",
      "startStroke": 0,
      "strokes": 7
    },
    {
      "radical": "八",
      "startStroke": 5,
      "strokes": 2
    },
    {
      "radical": "卜",
      "startStroke": 7,
      "strokes": 2,
      "variant": true
    },
    {
      "radical": "占",
      "startStroke": 7,
      "strokes": 5
    },
    {
      "radical": "口",
      "startStroke": 9,
      "strokes": 3
    }
  ],
  "sentences": [
    {
      "content": "部屋に貼るためよ",
      "furigana": "[部屋|へや]に[貼|は]るためよ",
      "translation_zh_CN": "我要把它放在我的房间里。"
    },
    {
      "content": "封筒に切手を貼りなさい。",
      "furigana": "[封筒|ふう|とう]に[切手|きっ|て]を[貼|は]りなさい。",
      "translation_zh_CN": "在信封上贴上邮票。"
    },
    {
      "content": "地図は壁に貼ってある。",
      "furigana": "[地図|ち|ず]は[壁|かべ]に[貼|は]ってある。",
      "translation_zh_CN": "地图贴在墙上。"
    },
    {
      "content": "封筒に切手を貼らなきゃ。",
      "furigana": "[封筒|ふう|とう]に[切手|きっ|て]を[貼|は]らなきゃ。",
      "translation_zh_CN": "我得在信封上贴邮票。"
    },
    {
      "content": "まあ、いいか、貼ったままで",
      "furigana": "まあ、いいか、[貼|は]ったままで",
      "translation_zh_CN": "嗯，好吧，留下它。"
    },
    {
      "content": "今その絵は壁に貼ってある。",
      "furigana": "[今|いま]その[絵|え]は[壁|かべ]に[貼|は]ってある。",
      "translation_zh_CN": "这幅画现在挂在墙上。"
    },
    {
      "content": "彼は手紙に切手を貼った。",
      "furigana": "[彼|かれ]は[手紙|て|がみ]に[切手|きっ|て]を[貼|は]った。",
      "translation_zh_CN": "他在信上贴了邮票。"
    },
    {
      "content": "封筒には切手を貼りましたか？",
      "furigana": "[封筒|ふう|とう]には[切手|きっ|て]を[貼|は]りましたか？",
      "translation_zh_CN": "你在信封上贴了邮票吗？"
    },
    {
      "content": "その写真は至る所に貼ってある。",
      "furigana": "その[写真|しゃ|しん]は[至|いた]る[所|ところ]に[貼|は]ってある。",
      "translation_zh_CN": "这张照片到处张贴。"
    },
    {
      "content": "彼は手にバンドエイドを貼った。",
      "furigana": "[彼|かれ]は[手|て]にバンドエイドを[貼|は]った。",
      "translation_zh_CN": "他在手上贴了创可贴。"
    },
    {
      "content": "地図は壁に貼ってある。",
      "furigana": "[地図|ち|ず]は[壁|かべ]に[貼|は]ってある。",
      "translation_zh_CN": "地图挂在墙上。"
    }
  ],
  "usages": [
    {
      "slug": "張る",
      "jlpt": [
        "jlpt-n3",
        "jlpt-n5"
      ],
      "japanese": [
        {
          "word": "張る",
          "reading": "はる"
        },
        {
          "word": "貼る",
          "reading": "はる"
        }
      ]
    },
    {
      "slug": "張り紙",
      "jlpt": [
        "jlpt-n1"
      ],
      "japanese": [
        {
          "word": "張り紙",
          "reading": "はりがみ"
        },
        {
          "word": "貼り紙",
          "reading": "はりがみ"
        },
        {
          "word": "はり紙",
          "reading": "はりがみ"
        },
        {
          "word": "張紙",
          "reading": "はりがみ"
        },
        {
          "word": "貼紙",
          "reading": "はりがみ"
        }
      ]
    },
    {
      "slug": "張り出す",
      "jlpt": [],
      "japanese": [
        {
          "word": "張り出す",
          "reading": "はりだす"
        },
        {
          "word": "貼り出す",
          "reading": "はりだす"
        }
      ]
    },
    {
      "slug": "張り付ける",
      "jlpt": [],
      "japanese": [
        {
          "word": "貼り付ける",
          "reading": "はりつける"
        },
        {
          "word": "貼付ける",
          "reading": "はりつける"
        },
        {
          "word": "貼りつける",
          "reading": "はりつける"
        },
        {
          "word": "張り付ける",
          "reading": "はりつける"
        },
        {
          "word": "張りつける",
          "reading": "はりつける"
        },
        {
          "word": "張付ける",
          "reading": "はりつける"
        }
      ]
    },
    {
      "slug": "貼り合わせる",
      "jlpt": [],
      "japanese": [
        {
          "word": "貼り合わせる",
          "reading": "はりあわせる"
        },
        {
          "word": "張り合わせる",
          "reading": "はりあわせる"
        }
      ]
    },
    {
      "slug": "貼付",
      "jlpt": [],
      "japanese": [
        {
          "word": "貼付",
          "reading": "ちょうふ"
        },
        {
          "word": "貼付",
          "reading": "てんぷ"
        }
      ]
    },
    {
      "slug": "張り替える",
      "jlpt": [],
      "japanese": [
        {
          "word": "張り替える",
          "reading": "はりかえる"
        },
        {
          "word": "貼り替える",
          "reading": "はりかえる"
        },
        {
          "word": "貼りかえる",
          "reading": "はりかえる"
        },
        {
          "word": "張替える",
          "reading": "はりかえる"
        },
        {
          "word": "張りかえる",
          "reading": "はりかえる"
        },
        {
          "word": "貼替える",
          "reading": "はりかえる"
        }
      ]
    },
    {
      "slug": "貼り込み",
      "jlpt": [],
      "japanese": [
        {
          "word": "貼り込み",
          "reading": "はりこみ"
        }
      ]
    },
    {
      "slug": "貼り出し",
      "jlpt": [],
      "japanese": [
        {
          "word": "貼り出し",
          "reading": "はりだし"
        }
      ]
    },
    {
      "slug": "貼付剤",
      "jlpt": [],
      "japanese": [
        {
          "word": "貼付剤",
          "reading": "ちょうふざい"
        }
      ]
    },
    {
      "slug": "張り替え",
      "jlpt": [],
      "japanese": [
        {
          "word": "張り替え",
          "reading": "はりかえ"
        },
        {
          "word": "張替え",
          "reading": "はりかえ"
        },
        {
          "word": "張替",
          "reading": "はりかえ"
        },
        {
          "word": "貼り替え",
          "reading": "はりかえ"
        },
        {
          "word": "貼替え",
          "reading": "はりかえ"
        },
        {
          "word": "貼替",
          "reading": "はりかえ"
        }
      ]
    },
    {
      "slug": "はり札",
      "jlpt": [],
      "japanese": [
        {
          "word": "はり札",
          "reading": "はりふだ"
        },
        {
          "word": "貼り札",
          "reading": "はりふだ"
        },
        {
          "word": "張り札",
          "reading": "はりふだ"
        },
        {
          "word": "張札",
          "reading": "はりふだ"
        }
      ]
    },
    {
      "slug": "貼付け",
      "jlpt": [],
      "japanese": [
        {
          "word": "貼り付け",
          "reading": "はりつけ"
        },
        {
          "word": "張り付け",
          "reading": "はりつけ"
        },
        {
          "word": "貼付け",
          "reading": "はりつけ"
        },
        {
          "word": "はり付け",
          "reading": "はりつけ"
        },
        {
          "word": "張付け",
          "reading": "はりつけ"
        }
      ]
    },
    {
      "slug": "張り付く",
      "jlpt": [],
      "japanese": [
        {
          "word": "張り付く",
          "reading": "はりつく"
        },
        {
          "word": "貼り付く",
          "reading": "はりつく"
        }
      ]
    },
    {
      "slug": "貼り箱",
      "jlpt": [],
      "japanese": [
        {
          "word": "貼り箱",
          "reading": "はりばこ"
        },
        {
          "word": "貼箱",
          "reading": "はりばこ"
        }
      ]
    },
    {
      "slug": "貼り絵",
      "jlpt": [],
      "japanese": [
        {
          "word": "貼り絵",
          "reading": "はりえ"
        }
      ]
    },
    {
      "slug": "貼り薬",
      "jlpt": [],
      "japanese": [
        {
          "word": "貼り薬",
          "reading": "はりぐすり"
        },
        {
          "word": "はり薬",
          "reading": "はりぐすり"
        }
      ]
    },
    {
      "slug": "貼り込む",
      "jlpt": [],
      "japanese": [
        {
          "word": "貼り込む",
          "reading": "はりこむ"
        },
        {
          "word": "貼りこむ",
          "reading": "はりこむ"
        }
      ]
    },
    {
      "slug": "貼合",
      "jlpt": [],
      "japanese": [
        {
          "word": "貼合",
          "reading": "てんごう"
        }
      ]
    }
  ]
}